gcm_toolkit/__init__.py
gcm_toolkit/gcm_dataset_collection.py
gcm_toolkit/gcmtools.py
gcm_toolkit/core/__init__.py
gcm_toolkit/core/const.py
gcm_toolkit/core/units.py
gcm_toolkit/core/writer.py
gcm_toolkit/exorad/__init__.py
gcm_toolkit/exorad/read_in.py
gcm_toolkit/exorad/utils.py
gcm_toolkit/tests/__init__.py
gcm_toolkit/tests/test_exorad.py
gcm_toolkit/tests/test_gcmt.py
gcm_toolkit/tests/test_gcmtools_common.py
gcm_toolkit/tests/test_interface.py
gcm_toolkit/tests/test_manipulations.py
gcm_toolkit/tests/test_plots.py
gcm_toolkit/tests/test_utils.py
gcm_toolkit/tests/test_writer.py
gcm_toolkit/utils/__init__.py
gcm_toolkit/utils/clouds.py
gcm_toolkit/utils/gcm_plotting.py
gcm_toolkit/utils/interface.py
gcm_toolkit/utils/manipulations.py
gcm_toolkit/utils/passport.py
gcm_toolkit/utils/read_and_write.py
gcm_toolkit-0.3.1.data/scripts/convert_to_gcmt
gcm_toolkit-0.3.1.dist-info/LICENSE.md
gcm_toolkit-0.3.1.dist-info/METADATA
gcm_toolkit-0.3.1.dist-info/WHEEL
gcm_toolkit-0.3.1.dist-info/top_level.txt
gcm_toolkit-0.3.1.dist-info/RECORD
