Metadata-Version: 2.1
Name: gcm-toolkit
Version: 0.3.1
Summary: postprocessing stuff
Home-page: https://github.com/exorad/gcmt
Author: Aaron David Schneider
Author-email: aarondavid.schneider@nbi.ku.dk
License: MIT
License-File: LICENSE.md
Requires-Dist: scipy (>=1.7.0)
Requires-Dist: numpy
Requires-Dist: f90nml
Requires-Dist: astropy
Requires-Dist: xarray
Requires-Dist: pyyaml
Requires-Dist: pre-commit
